lb/nightly/scheduler/__init__.py
lb/nightly/scheduler/_types.py
lb/nightly/scheduler/workflow.py
lb_nightly_scheduler-0.4.1.dist-info/LICENSE
lb_nightly_scheduler-0.4.1.dist-info/WHEEL
lb_nightly_scheduler-0.4.1.dist-info/METADATA
lb_nightly_scheduler-0.4.1.dist-info/RECORD
